ddtrace_api/__init__.py
ddtrace_api/constants.py
ddtrace_api/written.py
ddtrace_api-0.0.1.dist-info/licenses/LICENSE.apache2
ddtrace_api-0.0.1.dist-info/licenses/NOTICE
ddtrace_api-0.0.1.dist-info/METADATA
ddtrace_api-0.0.1.dist-info/WHEEL
ddtrace_api-0.0.1.dist-info/top_level.txt
ddtrace_api-0.0.1.dist-info/RECORD
